caplib4.py
caplib4-0.1.2.dist-info/LICENSE
caplib4-0.1.2.dist-info/METADATA
caplib4-0.1.2.dist-info/WHEEL
caplib4-0.1.2.dist-info/top_level.txt
caplib4-0.1.2.dist-info/RECORD
