Metadata-Version: 2.1
Name: caplib4
Version: 0.1.2
Summary: Analysis of capsid libraries
Home-page: https://github.com/damienmarsic/caplib4
Author: Damien Marsic
Author-email: damien.marsic@aliyun.com
Classifier: Programming Language :: Python :: 3
Classifier: License :: OSI Approved :: GNU General Public License v3 (GPLv3)
Classifier: Operating System :: OS Independent
Classifier: Intended Audience :: Science/Research
Classifier: Topic :: Scientific/Engineering :: Bio-Informatics
Requires-Python: >=3.6
License-File: LICENSE
